odrive_bindings/odrive_control_api.so
odrive_api-0.0.3.dist-info/WHEEL
odrive_api-0.0.3.dist-info/METADATA
odrive_api-0.0.3.dist-info/RECORD
