Metadata-Version: 2.1
Name: odrive_api
Summary: Custom python bindings for the Odrive motor controllers.
Requires-Python: >=3.12
Version: 0.0.3
